kami_light/Kami.py
kami_light/__init__.py
kami_light/kamutils/__init__.py
kami_light/kamutils/_utils.py
kami_light/metrics/__init__.py
kami_light/metrics/_base_metrics.py
kami_light/metrics/_shared_lib.py
kami_light/metrics/evaluation.py
kami_light/metrics/metrics_lib.so
kami_light/parser/__init__.py
kami_light/parser/parser_text.py
kami_light/preprocessing/__init__.py
kami_light/preprocessing/transformation.py
kamilib_light-0.1.1.dist-info/LICENSE
kamilib_light-0.1.1.dist-info/METADATA
kamilib_light-0.1.1.dist-info/WHEEL
kamilib_light-0.1.1.dist-info/top_level.txt
kamilib_light-0.1.1.dist-info/RECORD
