Metadata-Version: 2.1
Name: kamilib-light
Version: 0.1.1
Summary: A light version of KaMI-lib Python package containing only the transcription metrics module (without Kraken).
Home-page: https://github.com/KaMI-tools-project/KaMI-lib-light
Author: Lucas Terriel, Alix Chagué
Author-email: lucas.terriel@inria.fr, alix.chague@inria.fr
License: MIT
Keywords: HTR,OCR,Evaluation framework,metrics,handwritten text recognition,optical character recognition
Classifier: Programming Language :: Python
Classifier: License :: OSI Approved :: MIT License
Classifier: Intended Audience :: Developers
Classifier: Intended Audience :: Education
Classifier: Intended Audience :: Science/Research
Classifier: Operating System :: OS Independent
Classifier: Topic :: Software Development :: Libraries
Classifier: Topic :: Software Development :: Libraries :: Python Modules
Requires-Python: >=3.7
License-File: LICENSE
Requires-Dist: termcolor (==1.1.0)
Requires-Dist: unidecode (==1.3.4)
Requires-Dist: protobuf (==3.20.0)
Requires-Dist: python-Levenshtein (==0.12.2)
